{
  "id": "airlice",
  "name": "airlice",
  "layouts": {
    "LAYOUT": {
      "layout": [
        {
          "row": 0,
          "col": 0,
          "x": 0.75,
          "y": 1.5,
          "label": "~\n`"
        },
        {
          "row": 0,
          "col": 1,
          "x": 1.75,
          "y": 1.5,
          "label": "!\n1"
        },
        {
          "row": 0,
          "col": 2,
          "x": 2.75,
          "y": 1.4,
          "label": "@\n2"
        },
        {
          "row": 0,
          "col": 3,
          "x": 3.6500000000000004,
          "y": 2.5,
          "label": "#\n3",
          "r": 12,
          "rx": 8.5,
          "ry": 3.5
        },
        {
          "row": 0,
          "col": 4,
          "x": 4.65,
          "y": 2.5,
          "label": "$\n4",
          "r": 12,
          "rx": 8.5,
          "ry": 3.5
        },
        {
          "row": 0,
          "col": 5,
          "x": 5.65,
          "y": 2.5,
          "label": "%\n5",
          "r": 12,
          "rx": 8.5,
          "ry": 3.5
        },
        {
          "row": 0,
          "col": 6,
          "x": 6.65,
          "y": 2.5,
          "label": "^\n6",
          "r": 12,
          "rx": 8.5,
          "ry": 3.5
        },
        {
          "row": 0,
          "col": 7,
          "x": 8.8,
          "y": 2.45,
          "label": "&\n7",
          "r": -12,
          "rx": 8.5,
          "ry": 3.25
        },
        {
          "row": 0,
          "col": 8,
          "x": 9.8,
          "y": 2.45,
          "label": "*\n8",
          "r": -12,
          "rx": 8.5,
          "ry": 3.25
        },
        {
          "row": 0,
          "col": 9,
          "x": 10.8,
          "y": 2.45,
          "label": "(\n9",
          "r": -12,
          "rx": 8.5,
          "ry": 3.25
        },
        {
          "row": 0,
          "col": 10,
          "x": 11.8,
          "y": 2.45,
          "label": ")\n0",
          "r": -12,
          "rx": 8.5,
          "ry": 3.25
        },
        {
          "row": 0,
          "col": 11,
          "x": 12.7,
          "y": 1.4,
          "label": "_\n-"
        },
        {
          "row": 0,
          "col": 12,
          "x": 13.7,
          "y": 1.5,
          "label": "+\n="
        },
        {
          "row": 0,
          "col": 13,
          "x": 14.7,
          "y": 1.5,
          "label": "Delete",
          "u": 1.5
        },
        {
          "row": 1,
          "col": 0,
          "x": 0.5,
          "y": 2.5,
          "label": "⇤\n⇥\n\n\n\n\nTab",
          "u": 1.5
        },
        {
          "row": 1,
          "col": 1,
          "x": 2,
          "y": 2.5,
          "label": "Q"
        },
        {
          "row": 1,
          "col": 3,
          "x": 3.1500000000000004,
          "y": 3.5,
          "label": "W",
          "r": 12,
          "rx": 8.5,
          "ry": 3.5
        },
        {
          "row": 1,
          "col": 4,
          "x": 4.15,
          "y": 3.5,
          "label": "E",
          "r": 12,
          "rx": 8.5,
          "ry": 3.5
        },
        {
          "row": 1,
          "col": 5,
          "x": 5.15,
          "y": 3.5,
          "label": "R",
          "r": 12,
          "rx": 8.5,
          "ry": 3.5
        },
        {
          "row": 1,
          "col": 6,
          "x": 6.15,
          "y": 3.5,
          "label": "T",
          "r": 12,
          "rx": 8.5,
          "ry": 3.5
        },
        {
          "row": 1,
          "col": 7,
          "x": 8.3,
          "y": 3.45,
          "label": "Y",
          "r": -12,
          "rx": 8.5,
          "ry": 3.25
        },
        {
          "row": 1,
          "col": 8,
          "x": 9.3,
          "y": 3.45,
          "label": "U",
          "r": -12,
          "rx": 8.5,
          "ry": 3.25
        },
        {
          "row": 1,
          "col": 9,
          "x": 10.3,
          "y": 3.45,
          "label": "I",
          "r": -12,
          "rx": 8.5,
          "ry": 3.25
        },
        {
          "row": 1,
          "col": 10,
          "x": 11.3,
          "y": 3.45,
          "label": "O",
          "r": -12,
          "rx": 8.5,
          "ry": 3.25
        },
        {
          "row": 1,
          "col": 11,
          "x": 12.3,
          "y": 3.45,
          "label": "P",
          "r": -12,
          "rx": 8.5,
          "ry": 3.25
        },
        {
          "row": 1,
          "col": 12,
          "x": 13.45,
          "y": 2.5,
          "label": "{\n["
        },
        {
          "row": 1,
          "col": 13,
          "x": 14.45,
          "y": 2.5,
          "label": "}\n]"
        },
        {
          "row": 1,
          "col": 14,
          "x": 15.45,
          "y": 2.5,
          "label": "|\n\\"
        },
        {
          "row": 1,
          "col": 15,
          "x": 17,
          "y": 2.25,
          "label": "↑"
        },
        {
          "row": 2,
          "col": 0,
          "x": 0.5,
          "y": 3.5,
          "label": "Control",
          "u": 1.5
        },
        {
          "row": 2,
          "col": 1,
          "x": 2,
          "y": 3.5,
          "label": "A"
        },
        {
          "row": 2,
          "col": 3,
          "x": 3.4000000000000004,
          "y": 4.5,
          "label": "S",
          "r": 12,
          "rx": 8.5,
          "ry": 3.5
        },
        {
          "row": 2,
          "col": 4,
          "x": 4.4,
          "y": 4.5,
          "label": "D",
          "r": 12,
          "rx": 8.5,
          "ry": 3.5
        },
        {
          "row": 2,
          "col": 5,
          "x": 5.4,
          "y": 4.5,
          "label": "F",
          "r": 12,
          "rx": 8.5,
          "ry": 3.5
        },
        {
          "row": 2,
          "col": 6,
          "x": 6.4,
          "y": 4.5,
          "label": "G",
          "r": 12,
          "rx": 8.5,
          "ry": 3.5
        },
        {
          "row": 2,
          "col": 7,
          "x": 8.55,
          "y": 4.45,
          "label": "H",
          "r": -12,
          "rx": 8.5,
          "ry": 3.25
        },
        {
          "row": 2,
          "col": 8,
          "x": 9.55,
          "y": 4.45,
          "label": "J",
          "r": -12,
          "rx": 8.5,
          "ry": 3.25
        },
        {
          "row": 2,
          "col": 9,
          "x": 10.55,
          "y": 4.45,
          "label": "K",
          "r": -12,
          "rx": 8.5,
          "ry": 3.25
        },
        {
          "row": 2,
          "col": 10,
          "x": 11.55,
          "y": 4.45,
          "label": "L",
          "r": -12,
          "rx": 8.5,
          "ry": 3.25
        },
        {
          "row": 2,
          "col": 11,
          "x": 12.95,
          "y": 3.5,
          "label": ":\n;"
        },
        {
          "row": 2,
          "col": 12,
          "x": 13.95,
          "y": 3.5,
          "label": "\"\n'"
        },
        {
          "row": 2,
          "col": 13,
          "x": 14.95,
          "y": 3.5,
          "label": "↵ Enter",
          "u": 1.5
        },
        {
          "row": 2,
          "col": 15,
          "x": 17.5,
          "y": 3.25,
          "label": "↓"
        },
        {
          "row": 3,
          "col": 0,
          "x": 0.75,
          "y": 4.5,
          "label": "⇧ Shift",
          "u": 1.5
        },
        {
          "row": 3,
          "col": 1,
          "x": 2.25,
          "y": 4.5,
          "label": "Z"
        },
        {
          "row": 3,
          "col": 3,
          "x": 3.9000000000000004,
          "y": 5.5,
          "label": "X",
          "r": 12,
          "rx": 8.5,
          "ry": 3.5
        },
        {
          "row": 3,
          "col": 4,
          "x": 4.9,
          "y": 5.5,
          "label": "C",
          "r": 12,
          "rx": 8.5,
          "ry": 3.5
        },
        {
          "row": 3,
          "col": 5,
          "x": 5.9,
          "y": 5.5,
          "label": "V",
          "r": 12,
          "rx": 8.5,
          "ry": 3.5
        },
        {
          "row": 3,
          "col": 6,
          "x": 6.9,
          "y": 5.5,
          "label": "B",
          "r": 12,
          "rx": 8.5,
          "ry": 3.5
        },
        {
          "row": 3,
          "col": 7,
          "x": 8.8,
          "y": 5.45,
          "label": "N",
          "r": -12,
          "rx": 8.5,
          "ry": 3.25
        },
        {
          "row": 3,
          "col": 8,
          "x": 9.8,
          "y": 5.45,
          "label": "M",
          "r": -12,
          "rx": 8.5,
          "ry": 3.25
        },
        {
          "row": 3,
          "col": 9,
          "x": 10.8,
          "y": 5.45,
          "label": "<\n,",
          "r": -12,
          "rx": 8.5,
          "ry": 3.25
        },
        {
          "row": 3,
          "col": 10,
          "x": 11.8,
          "y": 5.45,
          "label": ">\n.",
          "r": -12,
          "rx": 8.5,
          "ry": 3.25
        },
        {
          "row": 3,
          "col": 11,
          "x": 13.45,
          "y": 4.5,
          "label": "?\n/"
        },
        {
          "row": 3,
          "col": 12,
          "x": 14.45,
          "y": 4.5,
          "label": "⇧ Shift",
          "u": 1.5
        },
        {
          "row": 3,
          "col": 14,
          "x": 16.75,
          "y": 4.5,
          "label": "↑"
        },
        {
          "row": 3,
          "col": 15,
          "x": 18,
          "y": 4.25,
          "label": "↓"
        },
        {
          "row": 4,
          "col": 0,
          "x": 1,
          "y": 5.5,
          "label": "Control",
          "u": 1.5
        },
        {
          "row": 4,
          "col": 3,
          "x": 4.15,
          "y": 6.5,
          "label": "Alt",
          "r": 12,
          "rx": 8.5,
          "ry": 3.5,
          "u": 1.25
        },
        {
          "row": 4,
          "col": 5,
          "x": 5.4,
          "y": 6.5,
          "label": "Fn",
          "r": 12,
          "rx": 8.5,
          "ry": 3.5,
          "u": 1.25
        },
        {
          "row": 4,
          "col": 6,
          "x": 6.65,
          "y": 6.5,
          "r": 12,
          "rx": 8.5,
          "ry": 3.5,
          "u": 1.25
        },
        {
          "row": 4,
          "col": 7,
          "x": 8.3,
          "y": 6.45,
          "r": -12,
          "rx": 8.5,
          "ry": 3.25,
          "u": 1.5
        },
        {
          "row": 4,
          "col": 8,
          "x": 9.8,
          "y": 6.45,
          "label": "Alt Gr",
          "r": -12,
          "rx": 8.5,
          "ry": 3.25
        },
        {
          "row": 4,
          "col": 9,
          "x": 10.8,
          "y": 6.45,
          "label": "Alt Gr",
          "r": -12,
          "rx": 8.5,
          "ry": 3.25
        },
        {
          "row": 4,
          "col": 10,
          "x": 11.8,
          "y": 6.45,
          "label": "Alt Gr",
          "r": -12,
          "rx": 8.5,
          "ry": 3.25,
          "u": 1.25
        },
        {
          "row": 4,
          "col": 11,
          "x": 14,
          "y": 5.5,
          "label": "Control",
          "u": 1.5
        },
        {
          "row": 4,
          "col": 12,
          "x": 15.75,
          "y": 5.5,
          "label": "←"
        },
        {
          "row": 4,
          "col": 14,
          "x": 16.75,
          "y": 5.5,
          "label": "↓"
        },
        {
          "row": 4,
          "col": 15,
          "x": 17.75,
          "y": 5.5,
          "label": "→"
        }
      ]
    }
  },
  "sensors": []
}